AUTHORS.rst
CONTRIBUTING.rst
HISTORY.rst
LICENSE
MANIFEST.in
README.md
README.rst
cinephile.py
cinephile.yaml
setup.py
cinephile.egg-info/PKG-INFO
cinephile.egg-info/SOURCES.txt
cinephile.egg-info/dependency_links.txt
cinephile.egg-info/entry_points.txt
cinephile.egg-info/requires.txt
cinephile.egg-info/top_level.txt
cinephile.egg-info/zip-safe