Metadata-Version: 1.0
Name: cinephile
Version: 1.0.2
Summary: Python CLI tool to scan movie directory         recursively, normalize the filename and retrieve useful         information from imdb.
Home-page: https://github.com/navinsylvester/cinephile
Author: Navin Sylvester
Author-email: navinsylvester@gmail.com
License: MIT License
Download-URL: https://github.com/navinsylvester/cinephile/tarball/master
Keywords: IMDB Movies Rating List
Platform: any
Classifier: Operating System :: POSIX
Classifier: Programming Language :: Python
Classifier: Environment :: Console
Classifier: Topic :: Internet
Classifier: Topic :: Internet :: WWW/HTTP
Classifier: Topic :: Utilities
